supabase_py_async/__init__.py
supabase_py_async/__version__.py
supabase_py_async/client_async.py
supabase_py_async/lib/__init__.py
supabase_py_async/lib/auth_client.py
supabase_py_async/lib/client_options.py
supabase_py_async/lib/realtime_client.py
supabase_py_async/types.py
supabase_py_async-2.5.6.dist-info/LICENSE
supabase_py_async-2.5.6.dist-info/METADATA
supabase_py_async-2.5.6.dist-info/WHEEL
supabase_py_async-2.5.6.dist-info/entry_points.txt
supabase_py_async-2.5.6.dist-info/RECORD
