Metadata-Version: 2.1
Name: supabase-py-async
Version: 2.5.6
Summary: supabase-py with async synax
Home-page: https://github.com/Atticuszz/supabase-py_async
License: MIT
Author: Atticuszz
Author-email: 1831768457@qq.com
Requires-Python: >=3.9,<4.0
Classifier: License :: OSI Approved :: MIT License
Classifier: Programming Language :: Python :: 3
Classifier: Programming Language :: Python :: 3.9
Classifier: Programming Language :: Python :: 3.10
Classifier: Programming Language :: Python :: 3.11
Classifier: Programming Language :: Python :: 3.12
Requires-Dist: aiohttp (>=3.9.0,<4.0.0)
Requires-Dist: commitizen (>=3.13.0,<4.0.0)
Requires-Dist: deprecation (>=2.1.0,<3.0.0)
Requires-Dist: gotrue (>=1.2,<3.0)
Requires-Dist: postgrest (>=0.13,<0.17)
Requires-Dist: realtime (>=1.0.2,<2.0.0)
Requires-Dist: storage3 (>=0.6.1,<0.8.0)
Requires-Dist: supafunc (==0.4.0)
Project-URL: Repository, https://github.com/Atticuszz/supabase-py_async
